archook/__init__.py
archook/archook.py
archook-1.2.0.dist-info/DESCRIPTION.rst
archook-1.2.0.dist-info/METADATA
archook-1.2.0.dist-info/RECORD
archook-1.2.0.dist-info/WHEEL
archook-1.2.0.dist-info/metadata.json
archook-1.2.0.dist-info/top_level.txt
