Metadata-Version: 2.0
Name: archook
Version: 1.2.0
Summary: Locates arcpy and makes it available to the running python distribution
Home-page: https://github.com/JamesRamm/archook
Author: James Ramm
Author-email: jamessramm@gmail.com
License: UNKNOWN
Platform: UNKNOWN
Classifier: Environment :: Console
Classifier: Intended Audience :: Science/Research
Classifier: Programming Language :: Python
Classifier: Topic :: Scientific/Engineering
Classifier: Operating System :: Microsoft :: Windows
